cad.py
neo_cad-0.1.1.dist-info/DESCRIPTION.rst
neo_cad-0.1.1.dist-info/METADATA
neo_cad-0.1.1.dist-info/RECORD
neo_cad-0.1.1.dist-info/WHEEL
neo_cad-0.1.1.dist-info/metadata.json
neo_cad-0.1.1.dist-info/top_level.txt
