Metadata-Version: 2.0
Name: neo-cad
Version: 0.1.1
Summary: Helper function to create, activate and deactivate Neo models.
Home-page: https://github.com/deone/cad
Author: Dayo Osikoya
Author-email: alwaysdeone@gmail.com
License: MIT
Keywords: rest http api json response django
Platform: UNKNOWN
Classifier: Development Status :: 5 - Production/Stable
Classifier: Intended Audience :: Developers
Classifier: Topic :: Software Development :: Build Tools
Classifier: License :: OSI Approved :: MIT License
Classifier: Programming Language :: Python :: 2
Classifier: Programming Language :: Python :: 2.6
Classifier: Programming Language :: Python :: 2.7
